ssp8162_power_supply/__init__.py
ssp8162_power_supply/power_supply.py
ssp8162_power_supply-0.1.0.dist-info/METADATA
ssp8162_power_supply-0.1.0.dist-info/WHEEL
ssp8162_power_supply-0.1.0.dist-info/top_level.txt
ssp8162_power_supply-0.1.0.dist-info/RECORD
