Metadata-Version: 2.2
Name: ssp8162_power_supply
Version: 0.1.0
Summary: A Python package to control the SSP-8162 power supply via serial communication.
Home-page: https://github.com/juliansteffens/ssp8162_power_supply
Author: Julian Steffens and Robin Binger
Author-email: juliansf@mail.uni-paderborn.de
Classifier: Programming Language :: Python :: 3
Classifier: Operating System :: OS Independent
Requires-Python: >=3.6
Requires-Dist: pyserial
Dynamic: author
Dynamic: author-email
Dynamic: classifier
Dynamic: description
Dynamic: description-content-type
Dynamic: home-page
Dynamic: requires-dist
Dynamic: requires-python
Dynamic: summary
